Metadata-Version: 2.1
Name: my-pm10-predictor
Version: 0.1
Requires-Dist: pandas
Requires-Dist: numpy
Requires-Dist: matplotlib
Requires-Dist: seaborn
Requires-Dist: scikit-learn
Requires-Dist: tensorflow
Requires-Dist: keras
